{
  "extensionModelLoaderDescriptor": {
    "id": "java",
    "attributes": {
      "type": "com.ioconnectservices.mule.internal.DatadogAPMExtension",
      "version": "3.0.0"
    }
  },
  "name": "Datadog APM",
  "requiredProduct": "MULE",
  "classLoaderModelLoaderDescriptor": {
    "id": "mule",
    "attributes": {
      "privilegedExportedPackages": [],
      "privilegedArtifactIds": [],
      "exportedPackages": [
        "com.ioconnectservices.mule.internal.parameters",
        "com.ioconnectservices.mule.api"
      ],
      "exportedResources": []
    }
  },
  "bundleDescriptorLoader": {
    "id": "mule",
    "attributes": {}
  },
  "minMuleVersion": "4.1.1"
}